.travis.yml
CHANGES.rst
LICENSE.txt
MANIFEST.in
Makefile
README.rst
appveyor.yml
bitbucket-pipelines.yml
build_zoltan.sh
requirements-test.txt
requirements.txt
setup.cfg
setup.py
shippable.yml
PySPH.egg-info/PKG-INFO
PySPH.egg-info/SOURCES.txt
PySPH.egg-info/dependency_links.txt
PySPH.egg-info/entry_points.txt
PySPH.egg-info/not-zip-safe
PySPH.egg-info/requires.txt
PySPH.egg-info/top_level.txt
docs/.DS_Store
docs/Makefile
docs/make.bat
docs/Images/dam-break-schematic.png
docs/Images/db3d.png
docs/Images/ldc-streamlines.png
docs/Images/local-remote-particles.png
docs/Images/local-remote.svg
docs/Images/periodic-domain-ghost-particle-tags.png
docs/Images/point-partition.png
docs/Images/pysph-examples-common-steps.graphml
docs/Images/pysph-examples-common-steps.png
docs/Images/pysph_viewer.png
docs/Images/rings-collision.png
docs/images/dam-break-schematic.png
docs/images/db3d.png
docs/images/ldc-streamlines.png
docs/images/local-remote-particles.png
docs/images/local-remote.svg
docs/images/periodic-domain-ghost-particle-tags.png
docs/images/point-partition.png
docs/images/pysph-examples-common-steps.graphml
docs/images/pysph-examples-common-steps.png
docs/images/pysph_viewer.png
docs/images/rings-collision.png
docs/source/conf.py
docs/source/index.rst
docs/source/installation.rst
docs/source/overview.rst
docs/source/using_pysph.rst
docs/source/design/equations.rst
docs/source/design/overview.rst
docs/source/design/solver_interfaces.rst
docs/source/design/working_with_particles.rst
docs/source/design/images/controller.png
docs/source/design/images/html_client.png
docs/source/design/images/particle-array.png
docs/source/design/images/pysph-modules.png
docs/source/design/images/sph-flowchart.png
docs/source/examples/index.rst
docs/source/examples/taylor_green.rst
docs/source/pyzoltan/overview.rst
docs/source/reference/application.rst
docs/source/reference/carray.rst
docs/source/reference/controller.rst
docs/source/reference/equations.rst
docs/source/reference/index.rst
docs/source/reference/integrator.rst
docs/source/reference/kernels.rst
docs/source/reference/nnps.rst
docs/source/reference/parallel_manager.rst
docs/source/reference/particle_array.rst
