Metadata-Version: 1.1
Name: PySPH
Version: 1.0a6
Summary: A general purpose Smoothed Particle Hydrodynamics framework
Home-page: http://github.com/pypr/pysph
Author: PySPH Developers
Author-email: pysph-dev@googlegroups.com
License: BSD
Keywords: SPH simulation computational fluid dynamics
Platform: Linux
Platform: Mac OS-X
Platform: Unix
Platform: Windows
Classifier: Development Status :: 3 - Alpha
Classifier: Environment :: Console
Classifier: Intended Audience :: Developers
Classifier: Intended Audience :: Science/Research
Classifier: License :: OSI Approved :: BSD License
Classifier: Natural Language :: English
Classifier: Operating System :: MacOS :: MacOS X
Classifier: Operating System :: Microsoft :: Windows
Classifier: Operating System :: POSIX
Classifier: Operating System :: Unix
Classifier: Programming Language :: Python
Classifier: Programming Language :: Python :: 3
Classifier: Topic :: Scientific/Engineering
Classifier: Topic :: Scientific/Engineering :: Physics
Classifier: Topic :: Software Development :: Libraries
